odoo8_addon_service_desk-8.0.1.1.0.99.dev25-py3.8-nspkg.pth
odoo_addons/service_desk/__init__.py
odoo_addons/service_desk/__openerp__.py
odoo_addons/service_desk/analytic_contact.py
odoo_addons/service_desk/analytic_contact_view.xml
odoo_addons/service_desk/project.py
odoo_addons/service_desk/service_desk_view.xml
odoo_addons/service_desk/i18n/ar.po
odoo_addons/service_desk/i18n/ca.po
odoo_addons/service_desk/i18n/de.po
odoo_addons/service_desk/i18n/el.po
odoo_addons/service_desk/i18n/el_GR.po
odoo_addons/service_desk/i18n/es.po
odoo_addons/service_desk/i18n/es_CR.po
odoo_addons/service_desk/i18n/es_ES.po
odoo_addons/service_desk/i18n/es_MX.po
odoo_addons/service_desk/i18n/es_VE.po
odoo_addons/service_desk/i18n/fi.po
odoo_addons/service_desk/i18n/fr.po
odoo_addons/service_desk/i18n/gl.po
odoo_addons/service_desk/i18n/hr.po
odoo_addons/service_desk/i18n/hr_HR.po
odoo_addons/service_desk/i18n/hu.po
odoo_addons/service_desk/i18n/it.po
odoo_addons/service_desk/i18n/ja.po
odoo_addons/service_desk/i18n/lt.po
odoo_addons/service_desk/i18n/lv.po
odoo_addons/service_desk/i18n/mk.po
odoo_addons/service_desk/i18n/mn.po
odoo_addons/service_desk/i18n/nl.po
odoo_addons/service_desk/i18n/nl_NL.po
odoo_addons/service_desk/i18n/pl.po
odoo_addons/service_desk/i18n/pt.po
odoo_addons/service_desk/i18n/pt_BR.po
odoo_addons/service_desk/i18n/pt_PT.po
odoo_addons/service_desk/i18n/ro.po
odoo_addons/service_desk/i18n/ru.po
odoo_addons/service_desk/i18n/service_desk.pot
odoo_addons/service_desk/i18n/sk_SK.po
odoo_addons/service_desk/i18n/sl.po
odoo_addons/service_desk/i18n/sv.po
odoo_addons/service_desk/i18n/tr.po
odoo_addons/service_desk/i18n/tr_TR.po
odoo_addons/service_desk/i18n/uk.po
odoo_addons/service_desk/i18n/zh_CN.po
odoo_addons/service_desk/static/description/icon.png
odoo8_addon_service_desk-8.0.1.1.0.99.dev25.dist-info/METADATA
odoo8_addon_service_desk-8.0.1.1.0.99.dev25.dist-info/WHEEL
odoo8_addon_service_desk-8.0.1.1.0.99.dev25.dist-info/namespace_packages.txt
odoo8_addon_service_desk-8.0.1.1.0.99.dev25.dist-info/top_level.txt
odoo8_addon_service_desk-8.0.1.1.0.99.dev25.dist-info/RECORD
